Workbook

Sheet Executive Summary & Portfolio
A1: AL GHAFOOR TOWER & MALL - CONSOLIDATED PROPERTY & PAYMENT RECORD
A3: Complete Investment & Payment Ledger | Unit 206 (File: ATM-14A-206-2) | Allottee: Muhammad Sikander
A5: ALLOTMENT & PROPERTY CREDENTIALS | G5: GRAND TOTAL INVESTMENT CONSOLIDATION
A6: Project Name | B6: Al Ghafoor Tower & Mall (Surjani Town Sector 12, Karachi) | G6: Total Property Cost (2022-2025) | H6: 2174000 | I6: Schedule (1.449M) + Loan (0.725M)
A7: Allottee Name | B7: Muhammad Sikander S/O M. Shah Jahan | G7: Net Utility Charges (2025-2028) | H7: ='Utility Charges Ledger'!H8 | I7: Net after Rs. 250,000 discount
A8: CNIC Number | B8: 42201-5534206-1 | G8: Grand Total Capital Outlay | H8: =H6+H7 | I8: Total flat cost + utility infrastructure
A9: Property Unit | B9: Unit 206 (Apartments / Residential) | G9: Historical Flat Payments Paid | H9: ='Historical Flat Ledger (22-25)'!F105 | I9: Total paid across 100 transactions
A10: File Number | B10: ATM-14A-206-2 (Undertaking Ref: ATM-14A-206-1) | G10: Utility Charges Paid to Date | H10: ='Utility Charges Ledger'!H9 | I10: Paid across 9 monthly installments
A11: Original Booking Date | B11: 27-Apr-2022 (Receipt No. 1730) | G11: Grand Total Paid Across All Dues | H11: =H9+H10 | I11: Total cumulative money paid to Al Ghafoor
A12: Utility Undertaking Date | B12: 26-Nov-2025 (Discount & Installment Undertaking) | G12: Grand Total Remaining Balance | H12: =H8-H11 | I12: Total remaining liability to complete property
A14: SECTION 1: FLAT PURCHASE & CONSTRUCTION INSTALLMENTS (2022 - 2025)
A15: Category / Component | B15: Scheduled Total | C15: Total Received | D15: Balance Dues | E15: Total Transactions | F15: Status & Notes
A16: Schedule Amount (Booking, Installments, Casting) | B16: 1449000 | C16: 1449000 | D16: 0 | E16: 64 Receipts | F16: 100% Fully Settled
A17: Bank / Builder Loan Installment Facility | B17: 725000 | C17: 509000 | D17: 216000 | E17: 36 Receipts | F17: Installments 1 to 24 (Partially balance)
A18: Extra Charges / Discounts | B18: 0 | C18: 0 | D18: 0 | E18: - | F18: No extra charges billed on primary ledger
A19: TOTAL PROPERTY COST (FLAT) | B19: =SUM(B16:B18) | C19: =SUM(C16:C18) | D19: =SUM(D16:D18) | E19: 100 Receipts | F19: Official Ledger Closed as of 15-Sep-2025
A21: SECTION 2: UTILITY INSTALLATION CHARGES & SETTLEMENT (2025 - 2028)
A22: Payment Phase | B22: Monthly Rate | C22: Total Scheduled | D22: Paid to Date | E22: Remaining Balance | F22: Phase Progress
A23: Year 1 (Months 01 - 12: Dec 25 - Nov 26) | B23: 15000 | C23: 180000 | D23: ='Utility Yearly Breakdown'!E5 | E23: ='Utility Yearly Breakdown'!F5 | F23: 9 / 12 Paid (Active)
A24: Year 2 (Months 13 - 24: Dec 26 - Nov 27) | B24: 20000 | C24: 240000 | D24: ='Utility Yearly Breakdown'!E6 | E24: ='Utility Yearly Breakdown'!F6 | F24: 0 / 12 Paid (Upcoming)
A25: Year 3 (Months 25 - 36: Dec 27 - Nov 28) | B25: 25000 | C25: 300000 | D25: ='Utility Yearly Breakdown'!E7 | E25: ='Utility Yearly Breakdown'!F7 | F25: 0 / 12 Paid (Upcoming)
A26: Month 37 Final Payment (Dec 2028) | B26: 230000 | C26: 230000 | D26: ='Utility Yearly Breakdown'!E8 | E26: ='Utility Yearly Breakdown'!F8 | F26: 0 / 1 Paid (Upcoming)
A27: TOTAL UTILITY CHARGES (NET) | B27: - | C27: =SUM(C23:C26) | D27: =SUM(D23:D26) | E27: =SUM(E23:E26) | F27: =TEXT(D27/C27, "0.00%") & " Completed"

Sheet Utility Charges Ledger
A1: AL GHAFOOR TOWER & MALL - UTILITY INSTALLATION CHARGES
A3: Utility Charges Payment Tracker (2025 - 2028) | Unit 206 (File: ATM-14A-206-2) | Allottee: Muhammad Sikander
B5: PROPERTY & ALLOTMENT DETAILS | G5: FINANCIAL SUMMARY & PAYMENT PROGRESS
B6: Project Name | C6: Al Ghafoor Tower & Mall (Surjani Town Sector 12, Karachi) | G6: Gross Demand Amount | H6: 1200000 | I6: Original demand before discount
B7: Allottee Name | C7: Muhammad Sikander S/O M. Shah Jahan | G7: Special Discount Received | H7: 250000 | I7: Discount approved per undertaking
B8: CNIC Number | C8: 42201-5534206-1 | G8: Net Total Payable | H8: =H6-H7 | I8: Final net liability across 37 months
B9: Property Unit | C9: Unit 206 (Apartments / Residential) | G9: Total Amount Paid to Date | H9: =SUM(F15:F51) | I9: Dynamic sum of all actual payments
B10: File Number | C10: ATM-14A-206-2 (Undertaking Ref: ATM-14A-206-1) | G10: Remaining Balance | H10: =H8-H9 | I10: Net amount remaining to be cleared
B11: Original Booking Date | C11: 27-Apr-2022 (Receipt No. 1730) | G11: Installments Paid / Total | H11: =TEXT(COUNT(F15:F51),"0") & " / 37 Paid (" & TEXT(COUNTIF(N15:N51,"Pending*"),"0") & " Remaining)" | I11: Installment count progress
B12: Utility Undertaking Date | C12: 26-Nov-2025 (Discount & Installment Undertaking) | G12: Overall Payment Progress | H12: =H9/H8 | I12: Percentage of net dues settled
A14: Inst # | B14: Period / Year | C14: Scheduled Month | D14: Scheduled Dues (PKR) | E14: Actual Payment Date | F14: Actual Paid (PKR) | G14: Payment Channel | H14: Bank / Raast Tx Ref # | I14: Official Receipt # | J14: Receipt Issue Date | K14: Official Invoice ID(s) | L14: Cumulative Paid (PKR) | M14: Remaining Balance (PKR) | N14: Status | O14: Linked Proof / File Name | P14: Notes & Invoice Breakdown
A15: Month 01 | B15: Year 1 (M01-M12) | C15: Dec 2025 | D15: 15000 | E15: 2025-12-24 | F15: 15000 | G15: Raast (Habib Metro) | H15: MPBL241225144252711403 | I15: 181DC | J15: 2026-01-10 | K15: 9519 | L15: =IF(ISNUMBER(F15), SUM(F$15:F15), "") | M15: =IF(ISNUMBER(F15), $H$8-L15, "") | N15: =IF(ISBLANK(F15), "Pending", IF(OR(I15="Pending", I15=""), "Paid (Receipt Pending)", "Paid & Verified")) | O15: 2025-12-24_Official_Receipt_181DC_Month_01_PKR_15000.jpeg | P15: DC Monthly Installment No. 1
A16: Month 02 | B16: Year 1 (M01-M12) | C16: Jan 2026 | D16: 15000 | E16: 2026-01-26 | F16: 15000 | G16: Raast (Habib Metro) | H16: MPBL260126104328932403 | I16: 262DC | J16: 2026-01-27 | K16: 9519 (5k) + 9550 (10k) | L16: =IF(ISNUMBER(F16), SUM(F$15:F16), "") | M16: =IF(ISNUMBER(F16), $H$8-L16, "") | N16: =IF(ISBLANK(F16), "Pending", IF(OR(I16="Pending", I16=""), "Paid (Receipt Pending)", "Paid & Verified")) | O16: 2026-01-26_Official_Receipt_262DC_Month_02_PKR_15000.jpeg | P16: Split: Inst 1 (5k) + Inst 2 (10k)
A17: Month 03 | B17: Year 1 (M01-M12) | C17: Feb 2026 | D17: 15000 | E17: 2026-02-28 | F17: 15000 | G17: Raast (Habib Metro) | H17: MPBL280226100658681456 | I17: 465DC | J17: 2026-03-03 | K17: 9550 (10k) + 10312 (5k) | L17: =IF(ISNUMBER(F17), SUM(F$15:F17), "") | M17: =IF(ISNUMBER(F17), $H$8-L17, "") | N17: =IF(ISBLANK(F17), "Pending", IF(OR(I17="Pending", I17=""), "Paid (Receipt Pending)", "Paid & Verified")) | O17: 2026-02-28_Official_Receipt_465DC_Month_03_PKR_15000.jpeg | P17: Split: Inst 2 (10k) + Inst 3 (5k)
A18: Month 04 | B18: Year 1 (M01-M12) | C18: Mar 2026 | D18: 15000 | E18: 2026-03-24 | F18: 15000 | G18: Raast (Habib Metro) | H18: MPBL240326215057922140 | I18: 575DC | J18: 2026-03-28 | K18: 10312 (15k) | L18: =IF(ISNUMBER(F18), SUM(F$15:F18), "") | M18: =IF(ISNUMBER(F18), $H$8-L18, "") | N18: =IF(ISBLANK(F18), "Pending", IF(OR(I18="Pending", I18=""), "Paid (Receipt Pending)", "Paid & Verified")) | O18: 2026-03-25_Official_Receipt_575DC_Month_04_PKR_15000.jpeg | P18: DC Monthly Installment No. 3 (Full 15k)
A19: Month 05 | B19: Year 1 (M01-M12) | C19: Apr 2026 | D19: 15000 | E19: 2026-04-21 | F19: 15000 | G19: Raast (Habib Metro) | H19: MPBL210426172846822380 | I19: 730DC | J19: 2026-04-25 | K19: 10313 (15k) | L19: =IF(ISNUMBER(F19), SUM(F$15:F19), "") | M19: =IF(ISNUMBER(F19), $H$8-L19, "") | N19: =IF(ISBLANK(F19), "Pending", IF(OR(I19="Pending", I19=""), "Paid (Receipt Pending)", "Paid & Verified")) | O19: 2026-04-21_Official_Receipt_730DC_Month_05_PKR_15000.jpeg | P19: DC Monthly Installment No. 4 (Full 15k)
A20: Month 06 | B20: Year 1 (M01-M12) | C20: May 2026 | D20: 15000 | E20: 2026-05-28 | F20: 15000 | G20: Raast (Habib Metro) | H20: MPBL280526145514180383 | I20: 898DC | J20: 2026-06-02 | K20: 10313 (5k) + 10314 (10k) | L20: =IF(ISNUMBER(F20), SUM(F$15:F20), "") | M20: =IF(ISNUMBER(F20), $H$8-L20, "") | N20: =IF(ISBLANK(F20), "Pending", IF(OR(I20="Pending", I20=""), "Paid (Receipt Pending)", "Paid & Verified")) | O20: 2026-05-29_Official_Receipt_898DC_Month_06_PKR_15000.jpeg | P20: Split: Inst 4 (5k) + Inst 5 (10k)
A21: Month 07 | B21: Year 1 (M01-M12) | C21: Jun 2026 | D21: 15000 | E21: 2026-06-23 | F21: 15000 | G21: Raast (Habib Metro) | H21: MPBL230626132859643986 | I21: 1028DC | J21: 2026-06-30 | K21: 10314 (10k) + 18899 (5k) | L21: =IF(ISNUMBER(F21), SUM(F$15:F21), "") | M21: =IF(ISNUMBER(F21), $H$8-L21, "") | N21: =IF(ISBLANK(F21), "Pending", IF(OR(I21="Pending", I21=""), "Paid (Receipt Pending)", "Paid & Verified")) | O21: 2026-06-23_Official_Receipt_1028DC_Month_07_PKR_15000.jpeg | P21: Split: Inst 5 (10k) + Inst 6 (5k)
A22: Month 08 | B22: Year 1 (M01-M12) | C22: Jul 2026 | D22: 15000 | E22: 2026-07-23 | F22: 15000 | G22: Raast (Habib Metro Alert) | H22: MPBL230726222144869000 | I22: 1197DC | J22: 2026-07-28 | K22: 18899 (15k) | L22: =IF(ISNUMBER(F22), SUM(F$15:F22), "") | M22: =IF(ISNUMBER(F22), $H$8-L22, "") | N22: =IF(ISBLANK(F22), "Pending", IF(OR(I22="Pending", I22=""), "Paid (Receipt Pending)", "Paid & Verified")) | O22: 2026-07-24_Official_Receipt_1197DC_Month_08_PKR_15000.jpeg | P22: DC Monthly Installment No. 6 (Full 15k) / Ref: 307262
A23: Month 09 | B23: Year 1 (M01-M12) | C23: Aug 2026 | D23: 15000 | E23: 2026-08-25 | F23: 15000 | G23: Raast (Habib Metro) | H23: MPBL250826073453943870 | I23: Pending | L23: =IF(ISNUMBER(F23), SUM(F$15:F23), "") | M23: =IF(ISNUMBER(F23), $H$8-L23, "") | N23: =IF(ISBLANK(F23), "Pending", IF(OR(I23="Pending", I23=""), "Paid (Receipt Pending)", "Paid & Verified")) | O23: 2026-08-25_Bank_Transfer_Receipt_Month_09_PKR_15000.jpeg | P23: Transfer completed; Awaiting official builder receipt
A24: Month 10 | B24: Year 1 (M01-M12) | C24: Sep 2026 | D24: 15000 | L24: =IF(ISNUMBER(F24), SUM(F$15:F24), "") | M24: =IF(ISNUMBER(F24), $H$8-L24, "") | N24: =IF(ISBLANK(F24), "Pending", IF(OR(I24="Pending", I24=""), "Paid (Receipt Pending)", "Paid & Verified")) | P24: Scheduled installment
A25: Month 11 | B25: Year 1 (M01-M12) | C25: Oct 2026 | D25: 15000 | L25: =IF(ISNUMBER(F25), SUM(F$15:F25), "") | M25: =IF(ISNUMBER(F25), $H$8-L25, "") | N25: =IF(ISBLANK(F25), "Pending", IF(OR(I25="Pending", I25=""), "Paid (Receipt Pending)", "Paid & Verified")) | P25: Scheduled installment
A26: Month 12 | B26: Year 1 (M01-M12) | C26: Nov 2026 | D26: 15000 | L26: =IF(ISNUMBER(F26), SUM(F$15:F26), "") | M26: =IF(ISNUMBER(F26), $H$8-L26, "") | N26: =IF(ISBLANK(F26), "Pending", IF(OR(I26="Pending", I26=""), "Paid (Receipt Pending)", "Paid & Verified")) | P26: Scheduled installment (Year 1 Completion)
A27: Month 13 | B27: Year 2 (M13-M24) | C27: Dec 2026 | D27: 20000 | L27: =IF(ISNUMBER(F27), SUM(F$15:F27), "") | M27: =IF(ISNUMBER(F27), $H$8-L27, "") | N27: =IF(ISBLANK(F27), "Pending", IF(OR(I27="Pending", I27=""), "Paid (Receipt Pending)", "Paid & Verified")) | P27: Scheduled installment
A28: Month 14 | B28: Year 2 (M13-M24) | C28: Jan 2027 | D28: 20000 | L28: =IF(ISNUMBER(F28), SUM(F$15:F28), "") | M28: =IF(ISNUMBER(F28), $H$8-L28, "") | N28: =IF(ISBLANK(F28), "Pending", IF(OR(I28="Pending", I28=""), "Paid (Receipt Pending)", "Paid & Verified")) | P28: Scheduled installment
A29: Month 15 | B29: Year 2 (M13-M24) | C29: Feb 2027 | D29: 20000 | L29: =IF(ISNUMBER(F29), SUM(F$15:F29), "") | M29: =IF(ISNUMBER(F29), $H$8-L29, "") | N29: =IF(ISBLANK(F29), "Pending", IF(OR(I29="Pending", I29=""), "Paid (Receipt Pending)", "Paid & Verified")) | P29: Scheduled installment
A30: Month 16 | B30: Year 2 (M13-M24) | C30: Mar 2027 | D30: 20000 | L30: =IF(ISNUMBER(F30), SUM(F$15:F30), "") | M30: =IF(ISNUMBER(F30), $H$8-L30, "") | N30: =IF(ISBLANK(F30), "Pending", IF(OR(I30="Pending", I30=""), "Paid (Receipt Pending)", "Paid & Verified")) | P30: Scheduled installment
A31: Month 17 | B31: Year 2 (M13-M24) | C31: Apr 2027 | D31: 20000 | L31: =IF(ISNUMBER(F31), SUM(F$15:F31), "") | M31: =IF(ISNUMBER(F31), $H$8-L31, "") | N31: =IF(ISBLANK(F31), "Pending", IF(OR(I31="Pending", I31=""), "Paid (Receipt Pending)", "Paid & Verified")) | P31: Scheduled installment
A32: Month 18 | B32: Year 2 (M13-M24) | C32: May 2027 | D32: 20000 | L32: =IF(ISNUMBER(F32), SUM(F$15:F32), "") | M32: =IF(ISNUMBER(F32), $H$8-L32, "") | N32: =IF(ISBLANK(F32), "Pending", IF(OR(I32="Pending", I32=""), "Paid (Receipt Pending)", "Paid & Verified")) | P32: Scheduled installment
A33: Month 19 | B33: Year 2 (M13-M24) | C33: Jun 2027 | D33: 20000 | L33: =IF(ISNUMBER(F33), SUM(F$15:F33), "") | M33: =IF(ISNUMBER(F33), $H$8-L33, "") | N33: =IF(ISBLANK(F33), "Pending", IF(OR(I33="Pending", I33=""), "Paid (Receipt Pending)", "Paid & Verified")) | P33: Scheduled installment
A34: Month 20 | B34: Year 2 (M13-M24) | C34: Jul 2027 | D34: 20000 | L34: =IF(ISNUMBER(F34), SUM(F$15:F34), "") | M34: =IF(ISNUMBER(F34), $H$8-L34, "") | N34: =IF(ISBLANK(F34), "Pending", IF(OR(I34="Pending", I34=""), "Paid (Receipt Pending)", "Paid & Verified")) | P34: Scheduled installment
A35: Month 21 | B35: Year 2 (M13-M24) | C35: Aug 2027 | D35: 20000 | L35: =IF(ISNUMBER(F35), SUM(F$15:F35), "") | M35: =IF(ISNUMBER(F35), $H$8-L35, "") | N35: =IF(ISBLANK(F35), "Pending", IF(OR(I35="Pending", I35=""), "Paid (Receipt Pending)", "Paid & Verified")) | P35: Scheduled installment
... A51: Month 37 | B51: Final (M37) | C51: Dec 2028 | D51: 230000 | L51: =IF(ISNUMBER(F51), SUM(F$15:F51), "") | M51: =IF(ISNUMBER(F51), $H$8-L51, "") | N51: =IF(ISBLANK(F51), "Pending", IF(OR(I51="Pending", I51=""), "Paid (Receipt Pending)", "Paid & Verified")) | P51: Final lump sum settlement payment
A52: TOTAL | D52: =SUM(D15:D51) | F52: =SUM(F15:F51) | L52: =MAX(L15:L51) | M52: =MIN(M15:M51) | N52: =TEXT(COUNT(F15:F51),"0") & " / 37 Paid"

Sheet Utility Yearly Breakdown
A1: AL GHAFOOR UTILITY CHARGES - YEARLY & PHASE BREAKDOWN
A4: Payment Phase | B4: Month Range | C4: Monthly Rate (PKR) | D4: Total Scheduled (PKR) | E4: Paid to Date (PKR) | F4: Remaining Balance (PKR) | G4: Months Cleared | H4: Phase Status
A5: Year 1 | B5: Months 01 - 12 (Dec 2025 - Nov 2026) | C5: 15000 | D5: =12*C5 | E5: =SUM('Utility Charges Ledger'!F15:F26) | F5: =D5-E5 | G5: =COUNT('Utility Charges Ledger'!F15:F26) & " / 12" | H5: ="Active (" & TEXT(12-COUNT('Utility Charges Ledger'!F15:F26),"0") & " Remaining)"
A6: Year 2 | B6: Months 13 - 24 (Dec 2026 - Nov 2027) | C6: 20000 | D6: =12*C6 | E6: =SUM('Utility Charges Ledger'!F27:F38) | F6: =D6-E6 | G6: =COUNT('Utility Charges Ledger'!F27:F38) & " / 12" | H6: ="Upcoming"
A7: Year 3 | B7: Months 25 - 36 (Dec 2027 - Nov 2028) | C7: 25000 | D7: =12*C7 | E7: =SUM('Utility Charges Ledger'!F39:F50) | F7: =D7-E7 | G7: =COUNT('Utility Charges Ledger'!F39:F50) & " / 12" | H7: ="Upcoming"
A8: Final Payment | B8: Month 37 (Dec 2028) | C8: 230000 | D8: =1*C8 | E8: =SUM('Utility Charges Ledger'!F51) | F8: =D8-E8 | G8: =COUNT('Utility Charges Ledger'!F51) & " / 1" | H8: ="Upcoming"
A9: GRAND TOTAL | C9: - | D9: =SUM(D5:D8) | E9: =SUM(E5:E8) | F9: =SUM(F5:F8) | G9: =COUNT('Utility Charges Ledger'!F15:F51) & " / 37" | H9: =TEXT(E9/D9, "0.00%") & " Completed"
A12: UNDERTAKING & PAYMENT TERMS SUMMARY
A13: 1. Original Demand: Rs. 1,200,000/- for Utility Installation Charges (K-Electric, SSGC, Water & Sewerage).
A14: 2. Approved Discount: Rs. 250,000/- granted by Al Ghafoor Builder / Developer.
A15: 3. Agreed Settlement Amount: Rs. 950,000/- payable across 37 monthly installments (Nov 2025 Undertaking).
A16: 4. Year 1 (Months 1 to 12): Rs. 15,000 per month (Total: Rs. 180,000).
A17: 5. Year 2 (Months 13 to 24): Rs. 20,000 per month (Total: Rs. 240,000).
A18: 6. Year 3 (Months 25 to 36): Rs. 25,000 per month (Total: Rs. 300,000).
A19: 7. Month 37 (Final Payment): Rs. 230,000 lump sum settlement.
A20: 8. Receiving Entity: AL GHAFOOR TRADING CO (Bank Alfalah / Raast System).

Sheet Historical Flat Ledger (22-25)
A1: AL GHAFOOR TOWERS & MALL - HISTORICAL FLAT PAYMENT LEDGER (2022 - 2025)
A3: Original Schedule & Loan Installments (100 Transactions) | Total Cost: PKR 2,174,000 | Received: PKR 1,958,000
B5: HISTORICAL CONTRACT BREAKDOWN
B6: Client Name | C6: Muhammad Sikandar
B7: File Number | C7: ATM-14A-206-2
B8: Unit / Type | C8: Unit 206 (Apartments)
B9: Total Cost of Flat | C9: 2174000
B10: Schedule Amount | C10: 1449000
B11: Loan Component | C11: 725000
B12: Total Received (Ledger) | C12: 1958000
B13: Closing Ledger Balance | C13: 216000
A15: Tx # | B15: Date | C15: Payment Method | D15: Status | E15: Payment Description / Category | F15: Amount Paid (PKR) | G15: Cumulative Received (PKR) | H15: Remaining Flat Balance (PKR) | I15: Cheque / Ref No | J15: Official Receipt #
A16: 1 | B16: 27/04/2022 | C16: Cash | D16: Cleared | E16: On Booking | F16: 50000 | G16: =SUM(F$16:F16) | H16: =2174000-G16 | I16: N/A | J16: 1730
A17: 2 | B17: 26/05/2022 | C17: Cash | D17: Cleared | E17: Monthly Installments No. 1 | F17: 8000 | G17: =SUM(F$16:F17) | H17: =2174000-G17 | I17: N/A | J17: 2021
A18: 3 | B18: 26/05/2022 | C18: Cash | D18: Cleared | E18: On Confirmation | F18: 50000 | G18: =SUM(F$16:F18) | H18: =2174000-G18 | I18: N/A | J18: 2021
A19: 4 | B19: 26/05/2022 | C19: Cash | D19: Cleared | E19: Monthly Installments No. 3 | F19: 2000 | G19: =SUM(F$16:F19) | H19: =2174000-G19 | I19: N/A | J19: 2021
A20: 5 | B20: 26/05/2022 | C20: Cash | D20: Cleared | E20: Monthly Installments No. 2 | F20: 8000 | G20: =SUM(F$16:F20) | H20: =2174000-G20 | I20: N/A | J20: 2021
A21: 6 | B21: 26/06/2022 | C21: Cash | D21: Cleared | E21: On Allocation | F21: 50000 | G21: =SUM(F$16:F21) | H21: =2174000-G21 | I21: N/A | J21: 2396
A22: 7 | B22: 26/06/2022 | C22: Cash | D22: Cleared | E22: Monthly Installments No. 3 | F22: 6000 | G22: =SUM(F$16:F22) | H22: =2174000-G22 | I22: N/A | J22: 2396
A23: 8 | B23: 28/07/2022 | C23: Cash | D23: Cleared | E23: Quarterly Payments No. 1 | F23: 30000 | G23: =SUM(F$16:F23) | H23: =2174000-G23 | I23: N/A | J23: 2706
A24: 9 | B24: 28/07/2022 | C24: Cash | D24: Cleared | E24: On Plinth | F24: 65000 | G24: =SUM(F$16:F24) | H24: =2174000-G24 | I24: N/A | J24: 2706
A25: 10 | B25: 28/07/2022 | C25: Cash | D25: Cleared | E25: Monthly Installments No. 4 | F25: 8000 | G25: =SUM(F$16:F25) | H25: =2174000-G25 | I25: N/A | J25: 2706
A26: 11 | B26: 18/08/2022 | C26: Cash | D26: Cleared | E26: On Start of Work | F26: 50000 | G26: =SUM(F$16:F26) | H26: =2174000-G26 | I26: N/A | J26: 2935
A27: 12 | B27: 06/09/2022 | C27: Cash | D27: Cleared | E27: Monthly Installments No. 5 | F27: 8000 | G27: =SUM(F$16:F27) | H27: =2174000-G27 | I27: N/A | J27: 3146
... A115: 100 | B115: 15/09/2025 | C115: Online | D115: Cleared | E115: Monthly Installments No. 41 | F115: 8000 | G115: =SUM(F$16:F115) | H115: =2174000-G115 | I115: 996390 | J115: 12229
A116: TOTAL | F116: =SUM(F16:F115) | G116: =MAX(G16:G115) | H116: =MIN(H16:H115) | I116: 100 Payments | J116: All Cleared

Sheet Receipt Vault & Image Index
A1: AL GHAFOOR UTILITY CHARGES - RECEIPT & DOCUMENT ARCHIVE
A4: Doc # | B4: Document Type | C4: Transaction / Event Date | D4: Amount (PKR) | E4: Reference / Receipt # | F4: Archived File Name in Folder | G4: Description & Verification Note
A5: 1 | B5: Historical Master Ledger | C5: 2022-04-27 to 2025-09-15 | D5: 1958000 | E5: ATM-14A-206-2 | F5: 00_Historical_Flat_Booking_and_Installment_Ledger_2022_2025.pdf | G5: Official Al Ghafoor Client Ledger (100 Transactions from booking to Sep 2025)
A6: 2 | B6: Payment Plan Schedule | C6: 2025-11-26 | D6: - | E6: 37 Months Schedule | F6: 00_Payment_Schedule_Utility_Charges.jpeg | G6: Official 37-month utility installment schedule breakdown
A7: 3 | B7: Legal Undertaking | C7: 2025-11-26 | D7: 950000 | E7: ATM-14A-206-1 | F7: 2025-11-26_Receipt_and_Undertaking_Utility_Charges.jpeg | G7: Signed Undertaking & Discount acknowledgment (Rs. 250k discount)
A8: 4 | B8: Bank Transfer (Month 1) | C8: 2025-12-24 | D8: 15000 | E8: MPBL241225144252711403 | F8: 2025-12-24_Bank_Transfer_Receipt_Month_01_PKR_15000.jpeg | G8: Habib Metro Raast online transfer to Al Ghafoor Trading Co
A9: 5 | B9: Official Receipt (Month 1) | C9: 2026-01-10 (Tx: 2025-12-24) | D9: 15000 | E9: 181DC (Inv: 9519) | F9: 2025-12-24_Official_Receipt_181DC_Month_01_PKR_15000.jpeg | G9: Al Ghafoor Towers and Mall official receipt (Online)
A10: 6 | B10: Bank Transfer (Month 2) | C10: 2026-01-26 | D10: 15000 | E10: MPBL260126104328932403 | F10: 2026-01-26_Bank_Transfer_Receipt_Month_02_PKR_15000.jpeg | G10: Habib Metro Raast online transfer to Al Ghafoor Trading Co
A11: 7 | B11: Official Receipt (Month 2) | C11: 2026-01-27 (Tx: 2026-01-26) | D11: 15000 | E11: 262DC (Inv: 9519 & 9550) | F11: 2026-01-26_Official_Receipt_262DC_Month_02_PKR_15000.jpeg | G11: Al Ghafoor official receipt (Split: 5,000 + 10,000)
A12: 8 | B12: Bank Transfer (Month 3) | C12: 2026-02-28 | D12: 15000 | E12: MPBL280226100658681456 | F12: 2026-02-28_Bank_Transfer_Receipt_Month_03_PKR_15000.jpeg | G12: Habib Metro Raast online transfer to Al Ghafoor Trading Co
A13: 9 | B13: Official Receipt (Month 3) | C13: 2026-03-03 (Tx: 2026-02-28) | D13: 15000 | E13: 465DC (Inv: 9550 & 10312) | F13: 2026-02-28_Official_Receipt_465DC_Month_03_PKR_15000.jpeg | G13: Al Ghafoor official receipt (Split: 10,000 + 5,000)
A14: 10 | B14: Bank Transfer (Month 4) | C14: 2026-03-24 | D14: 15000 | E14: MPBL240326215057922140 | F14: 2026-03-24_Bank_Transfer_Receipt_Month_04_PKR_15000.jpeg | G14: Habib Metro Raast online transfer to Al Ghafoor Trading Co
A15: 11 | B15: Official Receipt (Month 4) | C15: 2026-03-28 (Tx: 2026-03-25) | D15: 15000 | E15: 575DC (Inv: 10312) | F15: 2026-03-25_Official_Receipt_575DC_Month_04_PKR_15000.jpeg | G15: Al Ghafoor official receipt (Full 15,000 against Inv 10312)
A16: 12 | B16: Bank Transfer (Month 5) | C16: 2026-04-21 | D16: 15000 | E16: MPBL210426172846822380 | F16: 2026-04-21_Bank_Transfer_Receipt_Month_05_PKR_15000.jpeg | G16: Habib Metro Raast online transfer to Al Ghafoor Trading Co
A17: 13 | B17: Official Receipt (Month 5) | C17: 2026-04-25 (Tx: 2026-04-21) | D17: 15000 | E17: 730DC (Inv: 10313) | F17: 2026-04-21_Official_Receipt_730DC_Month_05_PKR_15000.jpeg | G17: Al Ghafoor official receipt (Full 15,000 against Inv 10313)
A18: 14 | B18: Bank Transfer (Month 6) | C18: 2026-05-28 | D18: 15000 | E18: MPBL280526145514180383 | F18: 2026-05-28_Bank_Transfer_Receipt_Month_06_PKR_15000.jpeg | G18: Habib Metro Raast online transfer to Al Ghafoor Trading Co
... A24: 20 | B24: Bank Transfer (Month 9) | C24: 2026-08-25 | D24: 15000 | E24: MPBL250826073453943870 | F24: 2026-08-25_Bank_Transfer_Receipt_Month_09_PKR_15000.jpeg | G24: Habib Metro Raast online transfer (Official receipt pending)
